BotLib/__init__.py
BotLib/bizarro.py
bizarro/__init__.py
bizarro/buttons/button_generator.py
bizarro/buttons/button_validator.py
bizarro/template/template_button.py
bizarro/template/template_generic.py
bizarro/template/template_list.py
bizarro/template/template_quick_reply.py
bizarro/utility/mother.py
bizarro/utility/tag.py
bizarro/utility/util.py
bizarro_lib/__init__.py
bizarro_lib/bizarro.py
bizarro_lib/button.py
bizarro_lib/button_template.py
bizarro_lib/button_validation.py
bizarro_lib/generic_template.py
bizarro_lib/list_template.py
bizarro_lib/mother.py
bizarro_lib/quick_re.py
bizarro_lib/tag.py
bizarro_lib/util.py
bizarro_lib/buttons/button_generator.py
bizarro_lib/buttons/button_validator.py
bizarro_lib/quick_reply/quick_re.py
bizarro_lib/template/button_template.py
bizarro_lib/template/generic_template.py
bizarro_lib/template/list_template.py
bizarro_lib/template/template_button.py
bizarro_lib/template/template_generic.py
bizarro_lib/template/template_list.py
bizarro_lib/template/template_quick_reply.py
bizarro_lib/utility/button.py
bizarro_lib/utility/button_validation.py
bizarro_lib/utility/mother.py
bizarro_lib/utility/tag.py
bizarro_lib/utility/util.py
bizarro-1.0.2a0.dist-info/LICENSE.txt
bizarro-1.0.2a0.dist-info/METADATA
bizarro-1.0.2a0.dist-info/WHEEL
bizarro-1.0.2a0.dist-info/entry_points.txt
bizarro-1.0.2a0.dist-info/top_level.txt
bizarro-1.0.2a0.dist-info/RECORD
