Metadata-Version: 2.1
Name: bizarro
Version: 1.0.2a0
Summary: UNKNOWN
Home-page: https://github.com/p1r-a-t3/FB_Bot
Author: p1r-a-t3
Author-email: ibtehaz.92@gmail.com
License: MIT
Platform: UNKNOWN
Classifier: Programming Language :: Python :: 3
Classifier: License :: OSI Approved :: MIT License
Classifier: Operating System :: OS Independent
Requires-Dist: phonenumbers
